[{"inputs":[],"stateMutability":"nonpayable","type":"constructor"},{"inputs":[],"name":"accuracy","outputs":[{"internalType":"uint256","name":"","type":"uint256"}],"stateMutability":"view","type":"function"},{"inputs":[],"name":"getAccuracy","outputs":[{"internalType":"uint256","name":"","type":"uint256"}],"stateMutability":"view","type":"function"},{"inputs":[],"name":"getLoss","outputs":[{"internalType":"uint256","name":"","type":"uint256"}],"stateMutability":"view","type":"function"},{"inputs":[],"name":"loss","outputs":[{"internalType":"uint256","name":"","type":"uint256"}],"stateMutability":"view","type":"function"},{"inputs":[{"internalType":"uint256","name":"_loss","type":"uint256"},{"internalType":"uint256","name":"_accuracy","type":"uint256"}],"name":"setMetrics","outputs":[],"stateMutability":"nonpayable","type":"function"}]